[
  {
    "instances": [
      {
        "file": "server/features/model-proxy/modelProxy.router.ts",
        "start_line": 9,
        "end_line": 15,
        "start_col": 29,
        "end_col": 62,
        "fragment": ", validate(modelQuerySchema), async (req, res) => {\n  const { provider, apiKey } = req.body;\n  if (apiKey && !service.validateKey(provider, apiKey)) {\n    return res.status(400).json({ error: 'Invalid API key format for provider: ' + provider });\n  }\n  try {\n    const models = await service.listModels(provider, apiKey);"
      },
      {
        "file": "server/features/model-proxy/modelProxy.router.ts",
        "start_line": 22,
        "end_line": 28,
        "start_col": 30,
        "end_col": 59,
        "fragment": ", validate(modelQuerySchema), async (req, res) => {\n  const { provider, apiKey } = req.body;\n  if (apiKey && !service.validateKey(provider, apiKey)) {\n    return res.status(400).json({ error: 'Invalid API key format for provider: ' + provider });\n  }\n  try {\n    const quota = await service.getQuota(provider, apiKey);"
      }
    ],
    "token_count": 66,
    "line_count": 7,
    "fingerprint": "dup:43bfbb22",
    "actions": [
      {
        "type": "extract-shared",
        "auto_fixable": false,
        "description": "Extract duplicated code (7 lines, 2 instances) into a shared function"
      },
      {
        "type": "suppress-line",
        "auto_fixable": false,
        "description": "Suppress with an inline comment above the duplicated code",
        "comment": "// fallow-ignore-next-line code-duplication"
      }
    ]
  }
]