{
  "version": "7",
  "dialect": "sqlite",
  "entries": [
    {
      "idx": 0,
      "version": "6",
      "when": 1779791836425,
      "tag": "0000_real_morbius",
      "breakpoints": true
    },
    {
      "idx": 1,
      "version": "6",
      "when": 1779989233339,
      "tag": "0001_split_chat_coder",
      "breakpoints": true
    },
    {
      "idx": 2,
      "version": "6",
      "when": 1780335839943,
      "tag": "0002_late_molten_man",
      "breakpoints": true
    },
    {
      "idx": 3,
      "version": "6",
      "when": 1780401899469,
      "tag": "0003_married_shocker",
      "breakpoints": true
    },
    {
      "idx": 4,
      "version": "6",
      "when": 1780461663398,
      "tag": "0004_robust_nocturne",
      "breakpoints": true
    },
    {
      "idx": 5,
      "version": "6",
      "when": 1780463467442,
      "tag": "0005_heavy_princess_powerful",
      "breakpoints": true
    },
    {
      "idx": 6,
      "version": "6",
      "when": 1780506650266,
      "tag": "0006_early_rictor",
      "breakpoints": true
    },
    {
      "idx": 7,
      "version": "6",
      "when": 1780548616156,
      "tag": "0007_reflective_morph",
      "breakpoints": true
    },
    {
      "idx": 8,
      "version": "6",
      "when": 1780549397127,
      "tag": "0008_hot_silk_fever",
      "breakpoints": true
    },
    {
      "idx": 9,
      "version": "6",
      "when": 1780553920065,
      "tag": "0009_tearful_the_stranger",
      "breakpoints": true
    }
  ]
}
